springable/__init__.py
springable/behavior_creation.py
springable/discover.py
springable/simulation.py
springable/visualization.py
springable/data/__init__.py
springable/data/article_csv_models/__init__.py
springable/data/article_csv_models/fig1a_model.csv
springable/data/article_csv_models/fig1b_model.csv
springable/data/article_csv_models/fig1e_model.csv
springable/data/article_csv_models/fig1f_model.csv
springable/data/article_csv_models/fig3a_model.csv
springable/data/article_csv_models/fig3b_model.csv
springable/data/article_csv_models/fig3c_model.csv
springable/data/article_csv_models/fig3d_model.csv
springable/data/article_csv_models/fig4d_model.csv
springable/data/article_csv_models/fig5abottom_model.csv
springable/data/article_csv_models/fig5atop_model.csv
springable/data/article_csv_models/fig5b_model.csv
springable/data/article_csv_models/fig5cleft_model.csv
springable/data/article_csv_models/fig5cright_model.csv
springable/data/article_csv_models/fig5d_model.csv
springable/data/examples_csv_models/__init__.py
springable/data/examples_csv_models/buckling.csv
springable/data/examples_csv_models/example_contact_distance_spring.csv
springable/data/examples_csv_models/example_nonlinear_angular_spring.csv
springable/data/examples_csv_models/example_nonlinear_area_spring.csv
springable/data/examples_csv_models/example_nonlinear_path_spring.csv
springable/data/examples_csv_models/example_nonlinear_spring_assembly.csv
springable/data/examples_csv_models/example_xy_distance_springs.csv
springable/data/examples_csv_models/pneunet.csv
springable/data/examples_csv_models/single_highly_nonlinear_spring.csv
springable/data/examples_csv_models/single_linear_spring.csv
springable/data/examples_csv_models/single_nonmonotonic_spring.csv
springable/data/examples_csv_models/single_softening_spring.csv
springable/data/examples_csv_models/single_stiffening_spring.csv
springable/data/examples_csv_models/two_springs_at_an_angle.csv
springable-1.0.1.dist-info/licenses/LICENSE
springable-1.0.1.dist-info/METADATA
springable-1.0.1.dist-info/WHEEL
springable-1.0.1.dist-info/top_level.txt
springable-1.0.1.dist-info/RECORD
