Metadata-Version: 2.4
Name: springable
Version: 1.0.1
Summary: Nonlinear spring assembly solver and visualization
Author: Paul Ducarme
Author-email: paulducarme@hotmail.com
Project-URL: Homepage, https://ducarme.github.io/springable/
Project-URL: Source, https://github.com/ducarme/springable
Project-URL: Issues, https://github.com/ducarme/springable/issues
Keywords: nonlinear,spring,simulation,animation,instability,snap-through
Classifier: Programming Language :: Python :: 3.10
Classifier: Programming Language :: Python :: 3.11
Classifier: Programming Language :: Python :: 3.12
Classifier: Programming Language :: Python :: 3.13
Classifier: License :: OSI Approved :: GNU General Public License v3 (GPLv3)
Classifier: Operating System :: OS Independent
Requires-Python: >=3.10
License-File: LICENSE
Requires-Dist: numpy
Requires-Dist: scipy
Requires-Dist: matplotlib
Requires-Dist: tomli; python_version < "3.11"
Dynamic: license-file
